LICENSE
MANIFEST.in
pyproject.toml
setup.cfg
setup.py
contextualbandits/__init__.py
contextualbandits/_cy_utils.pyx
contextualbandits/cy_cpp_helpers.cpp
contextualbandits/evaluation.py
contextualbandits/offpolicy.py
contextualbandits/online.py
contextualbandits/utils.py
contextualbandits.egg-info/PKG-INFO
contextualbandits.egg-info/SOURCES.txt
contextualbandits.egg-info/dependency_links.txt
contextualbandits.egg-info/requires.txt
contextualbandits.egg-info/top_level.txt
contextualbandits/linreg/__init__.py
contextualbandits/linreg/linreg_double.pyx
contextualbandits/linreg/linreg_float.pyx
contextualbandits/linreg/linreg_untyped.pxi